{
  "patrick mahomes": {
    "espnScoreProjection": 23.44081137898491,
    "espnLowScore": 18.519,
    "espnHighScore": 28.677,
    "espnOutsideProjection": 24.46158408,
    "espnSimulationProjection": 23.598
  },
  "josh allen": {
    "espnScoreProjection": 20.625955158893003,
    "espnLowScore": 13.321,
    "espnHighScore": 27.616,
    "espnOutsideProjection": 20.25282429,
    "espnSimulationProjection": 20.465
  },
  "jonathan taylor": {
    "espnScoreProjection": 22.89873627234737,
    "espnLowScore": 12.291,
    "espnHighScore": 26.078,
    "espnOutsideProjection": 25.63376694,
    "espnSimulationProjection": 19.184
  },
  "jalen hurts": {
    "espnScoreProjection": 19.652283213656233,
    "espnLowScore": 11.644,
    "espnHighScore": 26.47,
    "espnOutsideProjection": 21.82697754,
    "espnSimulationProjection": 19.028
  },
  "bijan robinson": {
    "espnScoreProjection": 24.29678840378198,
    "espnLowScore": 15.878,
    "espnHighScore": 26.7,
    "espnOutsideProjection": 26.7,
    "espnSimulationProjection": 22.209
  },
  "bo nix": {
    "espnScoreProjection": 18.072526851224197,
    "espnLowScore": 10.252,
    "espnHighScore": 25.364,
    "espnOutsideProjection": 21.15590775,
    "espnSimulationProjection": 16.913
  },
  "baker mayfield": {
    "espnScoreProjection": 19.71925495767091,
    "espnLowScore": 11.662,
    "espnHighScore": 26.487,
    "espnOutsideProjection": 18.37584532,
    "espnSimulationProjection": 19.046
  },
  "daniel jones": {
    "espnScoreProjection": 15.696698632230303,
    "espnLowScore": 9.864,
    "espnHighScore": 21.529,
    "espnOutsideProjection": 20.7,
    "espnSimulationProjection": 15.697
  },
  "drake maye": {
    "espnScoreProjection": 19.237518049650557,
    "espnLowScore": 10.963,
    "espnHighScore": 27.291,
    "espnOutsideProjection": 18.21313554,
    "espnSimulationProjection": 19.127
  },
  "dak prescott": {
    "espnScoreProjection": 19.239604677294587,
    "espnLowScore": 10.963,
    "espnHighScore": 27.292,
    "espnOutsideProjection": 18.26295331,
    "espnSimulationProjection": 19.127
  },
  "christian mccaffrey": {
    "espnScoreProjection": 19.54240574656057,
    "espnLowScore": 12.312,
    "espnHighScore": 22.878,
    "espnOutsideProjection": 21.61087599,
    "espnSimulationProjection": 17.096
  },
  "caleb williams": {
    "espnScoreProjection": 19.3533169315543,
    "espnLowScore": 11.163,
    "espnHighScore": 27.468,
    "espnOutsideProjection": 18.39849916,
    "espnSimulationProjection": 19.315
  },
  "jordan love": {
    "espnScoreProjection": 14.699994908697011,
    "espnLowScore": 8.868,
    "espnHighScore": 20.532,
    "espnOutsideProjection": 17.17723363,
    "espnSimulationProjection": 14.7
  },
  "jaxson dart": {
    "espnScoreProjection": 16.96319756083226,
    "espnLowScore": 8.456,
    "espnHighScore": 24.337,
    "espnOutsideProjection": 17.83987699,
    "espnSimulationProjection": 15.456
  },
  "joe flacco": {
    "espnScoreProjection": 17.194746515842397,
    "espnLowScore": 8.072,
    "espnHighScore": 24.614,
    "espnOutsideProjection": 15.4,
    "espnSimulationProjection": 16.343
  },
  "devon achane": {
    "espnScoreProjection": 17.969995664539223,
    "espnLowScore": 16.934,
    "espnHighScore": 19.59994842,
    "espnOutsideProjection": 19.59994842,
    "espnSimulationProjection": 17.97
  },
  "saquon barkley": {
    "espnScoreProjection": 15.231100137245562,
    "espnLowScore": 9.763,
    "espnHighScore": 20.699,
    "espnOutsideProjection": 16.90038511,
    "espnSimulationProjection": 15.231
  },
  "justin fields": {
    "espnScoreProjection": 19.777912924888494,
    "espnLowScore": 11.637,
    "espnHighScore": 26.55,
    "espnOutsideProjection": 19.39835645,
    "espnSimulationProjection": 19.064
  },
  "aaron rodgers": {
    "espnScoreProjection": 17.72058742867445,
    "espnLowScore": 10.183,
    "espnHighScore": 25.172,
    "espnOutsideProjection": 16.21055943,
    "espnSimulationProjection": 16.79
  },
  "jamarr chase": {
    "espnScoreProjection": 19.30077786593953,
    "espnLowScore": 18.264,
    "espnHighScore": 20.337,
    "espnOutsideProjection": 19.70770395,
    "espnSimulationProjection": 19.301
  },
  "cj stroud": {
    "espnScoreProjection": 18.23532445207352,
    "espnLowScore": 10.265,
    "espnHighScore": 25.411,
    "espnOutsideProjection": 17.32208849,
    "espnSimulationProjection": 16.941
  },
  "marcus mariota": {
    "espnScoreProjection": 17.819856311439246,
    "espnLowScore": 10.184,
    "espnHighScore": 25.195,
    "espnOutsideProjection": 16.94081284,
    "espnSimulationProjection": 16.801
  },
  "spencer rattler": {
    "espnScoreProjection": 14.480182688700033,
    "espnLowScore": 8.658,
    "espnHighScore": 20.302,
    "espnOutsideProjection": 15.70058729,
    "espnSimulationProjection": 14.48
  },
  "kirk cousins": {
    "espnScoreProjection": 15.120087005474495,
    "espnLowScore": 9.162,
    "espnHighScore": 21.078,
    "espnOutsideProjection": 14.8,
    "espnSimulationProjection": 15.12
  },
  "josh jacobs": {
    "espnScoreProjection": 18.189458016024695,
    "espnLowScore": 10.47,
    "espnHighScore": 21.349,
    "espnOutsideProjection": 19.22887941,
    "espnSimulationProjection": 15.91
  },
  "rachaad white": {
    "espnScoreProjection": 15.269289404306686,
    "espnLowScore": 9.797,
    "espnHighScore": 20.742,
    "espnOutsideProjection": 16.89416678,
    "espnSimulationProjection": 15.269
  },
  "derrick henry": {
    "espnScoreProjection": 15.46588000866009,
    "espnLowScore": 10.267,
    "espnHighScore": 20.664,
    "espnOutsideProjection": 16.1,
    "espnSimulationProjection": 15.466
  },
  "james cook": {
    "espnScoreProjection": 14.45774050681776,
    "espnLowScore": 9.033,
    "espnHighScore": 19.883,
    "espnOutsideProjection": 15.23222399,
    "espnSimulationProjection": 14.458
  },
  "mac jones": {
    "espnScoreProjection": 13.896792547838317,
    "espnLowScore": 6.409,
    "espnHighScore": 21.752,
    "espnOutsideProjection": 13.04141268,
    "espnSimulationProjection": 13.7
  },
  "javonte williams": {
    "espnScoreProjection": 15.461850607865196,
    "espnLowScore": 10.264,
    "espnHighScore": 20.66,
    "espnOutsideProjection": 16.17297221,
    "espnSimulationProjection": 15.462
  },
  "ceedee lamb": {
    "espnScoreProjection": 17.786332099303618,
    "espnLowScore": 11.516,
    "espnHighScore": 23.084,
    "espnOutsideProjection": 16.85855358,
    "espnSimulationProjection": 17.3
  },
  "andy dalton": {
    "espnScoreProjection": 17.605560357275255,
    "espnLowScore": 10.039,
    "espnHighScore": 26.802,
    "espnOutsideProjection": 15.71099342,
    "espnSimulationProjection": 18.421
  },
  "emeka egbuka": {
    "espnScoreProjection": 17.69969493886054,
    "espnLowScore": 11.47,
    "espnHighScore": 23.13,
    "espnOutsideProjection": 16.8593969,
    "espnSimulationProjection": 17.3
  },
  "rashee rice": {
    "espnScoreProjection": 15.176195522652357,
    "espnLowScore": 7.445,
    "espnHighScore": 21.299,
    "espnOutsideProjection": 17.24967624,
    "espnSimulationProjection": 13.638
  },
  "devonta smith": {
    "espnScoreProjection": 16.968156328304325,
    "espnLowScore": 7.72,
    "espnHighScore": 20.707,
    "espnOutsideProjection": 16.66114582,
    "espnSimulationProjection": 13.956
  },
  "courtland sutton": {
    "espnScoreProjection": 14.981784856493423,
    "espnLowScore": 7.622,
    "espnHighScore": 21.281,
    "espnOutsideProjection": 13.7,
    "espnSimulationProjection": 13.807
  },
  "breece hall": {
    "espnScoreProjection": 14.636080086861025,
    "espnLowScore": 9.173,
    "espnHighScore": 20.1,
    "espnOutsideProjection": 18.04707502,
    "espnSimulationProjection": 14.636
  },
  "tua tagovailoa": {
    "espnScoreProjection": 10.886845862589666,
    "espnLowScore": 6.437,
    "espnHighScore": 13.876,
    "espnOutsideProjection": 12.08970101,
    "espnSimulationProjection": 10.157
  },
  "jaylen warren": {
    "espnScoreProjection": 13.810267216137067,
    "espnLowScore": 8.401,
    "espnHighScore": 19.219,
    "espnOutsideProjection": 16.27109993,
    "espnSimulationProjection": 13.81
  },
  "quinshon judkins": {
    "espnScoreProjection": 11.712654494620264,
    "espnLowScore": 5.075,
    "espnHighScore": 17.525,
    "espnOutsideProjection": 12.3616929,
    "espnSimulationProjection": 10.563
  },
  "jk dobbins": {
    "espnScoreProjection": 12.567119239434469,
    "espnLowScore": 6.016,
    "espnHighScore": 19.763,
    "espnOutsideProjection": 13.41112481,
    "espnSimulationProjection": 12.89
  },
  "cam ward": {
    "espnScoreProjection": 15.526242129060158,
    "espnLowScore": 9.718,
    "espnHighScore": 21.335,
    "espnOutsideProjection": 12.81606972,
    "espnSimulationProjection": 15.526
  },
  "chris olave": {
    "espnScoreProjection": 17.9003795157246,
    "espnLowScore": 11.444,
    "espnHighScore": 23.156,
    "espnOutsideProjection": 16.86680989,
    "espnSimulationProjection": 17.3
  },
  "cam skattebo": {
    "espnScoreProjection": 13.615075551335103,
    "espnLowScore": 6.859,
    "espnHighScore": 20.22,
    "espnOutsideProjection": 14.32152889,
    "espnSimulationProjection": 12.96
  },
  "dk metcalf": {
    "espnScoreProjection": 12.716859240399595,
    "espnLowScore": 6.964,
    "espnHighScore": 18.931,
    "espnOutsideProjection": 14.69465484,
    "espnSimulationProjection": 12.068
  },
  "george pickens": {
    "espnScoreProjection": 16.36389127996186,
    "espnLowScore": 6.88,
    "espnHighScore": 20.355,
    "espnOutsideProjection": 14.30393903,
    "espnSimulationProjection": 13.375
  },
  "rome odunze": {
    "espnScoreProjection": 11.976793879584486,
    "espnLowScore": 6.953,
    "espnHighScore": 19.283,
    "espnOutsideProjection": 13.21767436,
    "espnSimulationProjection": 12.043
  },
  "dillon gabriel": {
    "espnScoreProjection": 15.460390072836837,
    "espnLowScore": 9.372,
    "espnHighScore": 21.549,
    "espnOutsideProjection": 12.22152398,
    "espnSimulationProjection": 15.46
  },
  "chase brown": {
    "espnScoreProjection": 11.516686158129437,
    "espnLowScore": 5.03,
    "espnHighScore": 17.416,
    "espnOutsideProjection": 12.3088893,
    "espnSimulationProjection": 10.489
  },
  "tetairoa mcmillan": {
    "espnScoreProjection": 15.427738070426921,
    "espnLowScore": 7.099,
    "espnHighScore": 20.848,
    "espnOutsideProjection": 13.41358642,
    "espnSimulationProjection": 13.157
  },
  "alvin kamara": {
    "espnScoreProjection": 13.771388508890908,
    "espnLowScore": 6.878,
    "espnHighScore": 20.399,
    "espnOutsideProjection": 14.32749929,
    "espnSimulationProjection": 13.639
  },
  "dandre swift": {
    "espnScoreProjection": 12.589438847674128,
    "espnLowScore": 11.553,
    "espnHighScore": 14.99985527,
    "espnOutsideProjection": 14.99985527,
    "espnSimulationProjection": 12.589
  },
  "stefon diggs": {
    "espnScoreProjection": 14.81858398476299,
    "espnLowScore": 7.308,
    "espnHighScore": 21.002,
    "espnOutsideProjection": 12.83267951,
    "espnSimulationProjection": 13.401
  },
  "tyler warren": {
    "espnScoreProjection": 11.90942960058884,
    "espnLowScore": 5.739,
    "espnHighScore": 13.321,
    "espnOutsideProjection": 13,
    "espnSimulationProjection": 9.526
  },
  "jaylen waddle": {
    "espnScoreProjection": 15.60681264120642,
    "espnLowScore": 7.014,
    "espnHighScore": 20.756,
    "espnOutsideProjection": 13.06359885,
    "espnSimulationProjection": 13.07
  },
  "tee higgins": {
    "espnScoreProjection": 14.160936121200269,
    "espnLowScore": 7.351,
    "espnHighScore": 20.793,
    "espnOutsideProjection": 12.43780471,
    "espnSimulationProjection": 13.12
  },
  "rico dowdle": {
    "espnScoreProjection": 12.19398882899572,
    "espnLowScore": 5.782,
    "espnHighScore": 19.544,
    "espnOutsideProjection": 12.74837978,
    "espnSimulationProjection": 12.663
  },
  "michael pittman": {
    "espnScoreProjection": 15.177019608108159,
    "espnLowScore": 7.489,
    "espnHighScore": 21.349,
    "espnOutsideProjection": 13.8,
    "espnSimulationProjection": 13.747
  },
  "xavier worthy": {
    "espnScoreProjection": 14.829496114293438,
    "espnLowScore": 7.309,
    "espnHighScore": 21.008,
    "espnOutsideProjection": 12.54882019,
    "espnSimulationProjection": 13.402
  },
  "rhamondre stevenson": {
    "espnScoreProjection": 11.70879957194761,
    "espnLowScore": 5.899,
    "espnHighScore": 16.149,
    "espnOutsideProjection": 12.36441891,
    "espnSimulationProjection": 10.13
  },
  "darnell mooney": {
    "espnScoreProjection": 14.727761284192342,
    "espnLowScore": 7.581,
    "espnHighScore": 20.912,
    "espnOutsideProjection": 12.2,
    "espnSimulationProjection": 13.443
  },
  "isiah pacheco": {
    "espnScoreProjection": 10.496804937245447,
    "espnLowScore": 3.236,
    "espnHighScore": 17.422,
    "espnOutsideProjection": 11.42340257,
    "espnSimulationProjection": 9.671
  },
  "romeo doubs": {
    "espnScoreProjection": 14.051509126767169,
    "espnLowScore": 7.269,
    "espnHighScore": 20.664,
    "espnOutsideProjection": 12.1771376,
    "espnSimulationProjection": 13.154
  },
  "zay flowers": {
    "espnScoreProjection": 14.15123656582993,
    "espnLowScore": 7.349,
    "espnHighScore": 20.791,
    "espnOutsideProjection": 12.8,
    "espnSimulationProjection": 13.116
  },
  "wandale robinson": {
    "espnScoreProjection": 13.74994454344728,
    "espnLowScore": 12.714,
    "espnHighScore": 14.786,
    "espnOutsideProjection": 13.17669908,
    "espnSimulationProjection": 13.75
  },
  "tucker kraft": {
    "espnScoreProjection": 8.870189382257141,
    "espnLowScore": 4.448,
    "espnHighScore": 13.261,
    "espnOutsideProjection": 10.4,
    "espnSimulationProjection": 8.044
  },
  "jacory croskeymerritt": {
    "espnScoreProjection": 10.956736304538646,
    "espnLowScore": 4.433,
    "espnHighScore": 16.744,
    "espnOutsideProjection": 11.53117042,
    "espnSimulationProjection": 9.512
  },
  "dallas goedert": {
    "espnScoreProjection": 10.934925249682163,
    "espnLowScore": 5.201,
    "espnHighScore": 12.518,
    "espnOutsideProjection": 12.38600402,
    "espnSimulationProjection": 9.1
  },
  "woody marks": {
    "espnScoreProjection": 9.983203156243412,
    "espnLowScore": 2.443,
    "espnHighScore": 18.009,
    "espnOutsideProjection": 10.84687772,
    "espnSimulationProjection": 8.884
  },
  "george kittle": {
    "espnScoreProjection": 10.528727565177519,
    "espnLowScore": 5.024,
    "espnHighScore": 12.364,
    "espnOutsideProjection": 10.76923529,
    "espnSimulationProjection": 8.865
  },
  "chuba hubbard": {
    "espnScoreProjection": 10.826489311472098,
    "espnLowScore": 4.398,
    "espnHighScore": 16.679,
    "espnOutsideProjection": 11.95102091,
    "espnSimulationProjection": 9.446
  },
  "khalil shakir": {
    "espnScoreProjection": 13.53553614871158,
    "espnLowScore": 7.14,
    "espnHighScore": 20.481,
    "espnOutsideProjection": 11.7,
    "espnSimulationProjection": 12.948
  },
  "jake ferguson": {
    "espnScoreProjection": 11.400826084136007,
    "espnLowScore": 5.419,
    "espnHighScore": 13.1,
    "espnOutsideProjection": 13.1,
    "espnSimulationProjection": 9.22
  },
  "tony pollard": {
    "espnScoreProjection": 9.105686845556153,
    "espnLowScore": 3.513,
    "espnHighScore": 15.118,
    "espnOutsideProjection": 9.73704212,
    "espnSimulationProjection": 7.975
  },
  "kyle pitts sr": {
    "espnScoreProjection": 9.368380999948979,
    "espnLowScore": 3.722,
    "espnHighScore": 11.843,
    "espnOutsideProjection": 10.8,
    "espnSimulationProjection": 7.782
  },
  "rashid shaheed": {
    "espnScoreProjection": 14.797595593996077,
    "espnLowScore": 7.569,
    "espnHighScore": 20.934,
    "espnOutsideProjection": 12.16513142,
    "espnSimulationProjection": 13.435
  },
  "terry mclaurin": {
    "espnScoreProjection": 13.846904746809754,
    "espnLowScore": 7.239,
    "espnHighScore": 20.599,
    "espnOutsideProjection": 11.83524023,
    "espnSimulationProjection": 13.082
  },
  "matthew golden": {
    "espnScoreProjection": 10.478278158487836,
    "espnLowScore": 5.317,
    "espnHighScore": 18.273,
    "espnOutsideProjection": 10.26634545,
    "espnSimulationProjection": 10.539
  },
  "dalton schultz": {
    "espnScoreProjection": 7.466031763250134,
    "espnLowScore": 2.728,
    "espnHighScore": 11.608,
    "espnOutsideProjection": 9.67856898,
    "espnSimulationProjection": 7.168
  },
  "travis kelce": {
    "espnScoreProjection": 10.134415035434591,
    "espnLowScore": 4.885,
    "espnHighScore": 12.131,
    "espnOutsideProjection": 10.92485251,
    "espnSimulationProjection": 9.154
  },
  "tez johnson": {
    "espnScoreProjection": 11.466646054272449,
    "espnLowScore": 6.858,
    "espnHighScore": 19.135,
    "espnOutsideProjection": 8.91640334,
    "espnSimulationProjection": 11.845
  },
  "jauan jennings": {
    "espnScoreProjection": 12.19707138846802,
    "espnLowScore": 6.996,
    "espnHighScore": 19.432,
    "espnOutsideProjection": 9.04453336,
    "espnSimulationProjection": 12.148
  },
  "dj moore": {
    "espnScoreProjection": 9.72369029864612,
    "espnLowScore": 4.347,
    "espnHighScore": 17.239,
    "espnOutsideProjection": 10.34754423,
    "espnSimulationProjection": 9.169
  },
  "dalton kincaid": {
    "espnScoreProjection": 9.280424723560438,
    "espnLowScore": 3.775,
    "espnHighScore": 11.788,
    "espnOutsideProjection": 9.80256608,
    "espnSimulationProjection": 7.782
  },
  "keon coleman": {
    "espnScoreProjection": 12.868569488728006,
    "espnLowScore": 7.109,
    "espnHighScore": 18.961,
    "espnOutsideProjection": 10.20384154,
    "espnSimulationProjection": 12.157
  },
  "cade otton": {
    "espnScoreProjection": 8.728192785261104,
    "espnLowScore": 4.357,
    "espnHighScore": 13.162,
    "espnOutsideProjection": 9.90469329,
    "espnSimulationProjection": 7.939
  },
  "troy franklin": {
    "espnScoreProjection": 12.599964167649706,
    "espnLowScore": 6.432,
    "espnHighScore": 18.444,
    "espnOutsideProjection": 10.85551836,
    "espnSimulationProjection": 12.438
  },
  "tyler allgeier": {
    "espnScoreProjection": 9.654771151469234,
    "espnLowScore": 2.41,
    "espnHighScore": 17.89,
    "espnOutsideProjection": 8,
    "espnSimulationProjection": 8.787
  },
  "jerry jeudy": {
    "espnScoreProjection": 13.289157798698596,
    "espnLowScore": 7.456,
    "espnHighScore": 20.168,
    "espnOutsideProjection": 11.10456031,
    "espnSimulationProjection": 12.999
  },
  "alec pierce": {
    "espnScoreProjection": 10.227319847944813,
    "espnLowScore": 5.268,
    "espnHighScore": 18.265,
    "espnOutsideProjection": 7.7,
    "espnSimulationProjection": 10.468
  },
  "mason taylor": {
    "espnScoreProjection": 5.3618663640491775,
    "espnLowScore": 2.092,
    "espnHighScore": 11.666,
    "espnOutsideProjection": 8.89731692,
    "espnSimulationProjection": 4.688
  },
  "josh downs": {
    "espnScoreProjection": 11.610640577330292,
    "espnLowScore": 6.873,
    "espnHighScore": 19.177,
    "espnOutsideProjection": 10.9,
    "espnSimulationProjection": 11.891
  },
  "hunter henry": {
    "espnScoreProjection": 8.808285620795482,
    "espnLowScore": 4.439,
    "espnHighScore": 13.234,
    "espnOutsideProjection": 9.37641229,
    "espnSimulationProjection": 8.023
  },
  "harold fannin": {
    "espnScoreProjection": 9.126957787921812,
    "espnLowScore": 3.915,
    "espnHighScore": 11.726,
    "espnOutsideProjection": 9.62207481,
    "espnSimulationProjection": 7.82
  },
  "marvin mims": {
    "espnScoreProjection": 11.428579187141574,
    "espnLowScore": 6.849,
    "espnHighScore": 19.124,
    "espnOutsideProjection": 8.7178533,
    "espnSimulationProjection": 11.829
  },
  "kendrick bourne": {
    "espnScoreProjection": 10.048566542032802,
    "espnLowScore": 5.23,
    "espnHighScore": 18.209,
    "espnOutsideProjection": 8.40033357,
    "espnSimulationProjection": 10.395
  },
  "evan engram": {
    "espnScoreProjection": 9.126757496833592,
    "espnLowScore": 3.915,
    "espnHighScore": 11.726,
    "espnOutsideProjection": 9.86033932,
    "espnSimulationProjection": 7.82
  },
  "tyjae spears": {
    "espnScoreProjection": 9.280279923983354,
    "espnLowScore": 3.411,
    "espnHighScore": 15.033,
    "espnOutsideProjection": 9.51311629,
    "espnSimulationProjection": 7.877
  },
  "zach ertz": {
    "espnScoreProjection": 8.020630379721984,
    "espnLowScore": 3.716,
    "espnHighScore": 12.41,
    "espnOutsideProjection": 9.04897122,
    "espnSimulationProjection": 8.063
  },
  "jaylin noel": {
    "espnScoreProjection": 12.400331849348651,
    "espnLowScore": 6.278,
    "espnHighScore": 18.237,
    "espnOutsideProjection": 9.87986102,
    "espnSimulationProjection": 12.258
  },
  "elic ayomanor": {
    "espnScoreProjection": 12.991694152035,
    "espnLowScore": 7.253,
    "espnHighScore": 19.108,
    "espnOutsideProjection": 10.85211076,
    "espnSimulationProjection": 12.285
  },
  "nick chubb": {
    "espnScoreProjection": 8.917333434717788,
    "espnLowScore": 3.554,
    "espnHighScore": 14.87,
    "espnOutsideProjection": 9.2815322,
    "espnSimulationProjection": 7.947
  },
  "sterling shepard": {
    "espnScoreProjection": 9.197355043752061,
    "espnLowScore": 2.344,
    "espnHighScore": 14.501,
    "espnOutsideProjection": 7.96531107,
    "espnSimulationProjection": 8.422
  },
  "kayshon boutte": {
    "espnScoreProjection": 10.800165725924355,
    "espnLowScore": 6.071,
    "espnHighScore": 18.776,
    "espnOutsideProjection": 7.64644147,
    "espnSimulationProjection": 11.058
  },
  "kyle monangai": {
    "espnScoreProjection": 8.367772275796922,
    "espnLowScore": 3.349,
    "espnHighScore": 14.398,
    "espnOutsideProjection": 8.5346812,
    "espnSimulationProjection": 7.579
  },
  "xavier legette": {
    "espnScoreProjection": 11.44870891325285,
    "espnLowScore": 6.854,
    "espnHighScore": 19.13,
    "espnOutsideProjection": 8.46127224,
    "espnSimulationProjection": 11.838
  },
  "juwan johnson": {
    "espnScoreProjection": 8.727186956150168,
    "espnLowScore": 4.357,
    "espnHighScore": 13.162,
    "espnOutsideProjection": 9.5890178,
    "espnSimulationProjection": 7.939
  },
  "theo johnson": {
    "espnScoreProjection": 8.859940965669894,
    "espnLowScore": 4.446,
    "espnHighScore": 13.257,
    "espnOutsideProjection": 9.53656502,
    "espnSimulationProjection": 8.041
  },
  "jayden higgins": {
    "espnScoreProjection": 8.797303230881202,
    "espnLowScore": 3.275,
    "espnHighScore": 13.891,
    "espnOutsideProjection": 9.0129416,
    "espnSimulationProjection": 8.583
  },
  "malik washington": {
    "espnScoreProjection": 10.895413152273049,
    "espnLowScore": 6.501,
    "espnHighScore": 18.468,
    "espnOutsideProjection": 8.96284744,
    "espnSimulationProjection": 11.141
  },
  "darius slayton": {
    "espnScoreProjection": 11.17243026615138,
    "espnLowScore": 6.616,
    "espnHighScore": 18.627,
    "espnOutsideProjection": 8.38422034,
    "espnSimulationProjection": 11.303
  },
  "chimere dike": {
    "espnScoreProjection": 12.528927939629243,
    "espnLowScore": 6.383,
    "espnHighScore": 18.425,
    "espnOutsideProjection": 9.53871468,
    "espnSimulationProjection": 12.404
  },
  "calvin austin": {
    "espnScoreProjection": 11.105436676586967,
    "espnLowScore": 6.602,
    "espnHighScore": 18.604,
    "espnOutsideProjection": 8.20607884,
    "espnSimulationProjection": 11.276
  },
  "colston loveland": {
    "espnScoreProjection": 5.626139264168534,
    "espnLowScore": 2.149,
    "espnHighScore": 12.155,
    "espnOutsideProjection": 6.54282457,
    "espnSimulationProjection": 4.863
  },
  "olamide zaccheaus": {
    "espnScoreProjection": 7.300671519693269,
    "espnLowScore": 1.989,
    "espnHighScore": 11.563,
    "espnOutsideProjection": 7.92899907,
    "espnSimulationProjection": 6.776
  },
  "mark andrews": {
    "espnScoreProjection": 6.377026669008851,
    "espnLowScore": 2.016,
    "espnHighScore": 11.156,
    "espnOutsideProjection": 8.6,
    "espnSimulationProjection": 6.586
  },
  "xavier hutchinson": {
    "espnScoreProjection": 7.975541532623442,
    "espnLowScore": 1.861,
    "espnHighScore": 12.908,
    "espnOutsideProjection": 8.50765827,
    "espnSimulationProjection": 7.384
  },
  "rj harvey": {
    "espnScoreProjection": 7.536324963632827,
    "espnLowScore": 2.553,
    "espnHighScore": 11.535,
    "espnOutsideProjection": 7.24885194,
    "espnSimulationProjection": 5.54
  },
  "jalen coker": {
    "espnScoreProjection": 9.04169109701052,
    "espnLowScore": 3.561,
    "espnHighScore": 13.812,
    "espnOutsideProjection": 6.59277306,
    "espnSimulationProjection": 8.686
  },
  "brashard smith": {
    "espnScoreProjection": 4.908976203744723,
    "espnLowScore": 1.602,
    "espnHighScore": 7.749,
    "espnOutsideProjection": 4.65217265,
    "espnSimulationProjection": 4.312
  },
  "van jefferson": {
    "espnScoreProjection": 10.964261578116943,
    "espnLowScore": 6.572,
    "espnHighScore": 18.556,
    "espnOutsideProjection": 7.61615516,
    "espnSimulationProjection": 11.218
  },
  "kenneth gainwell": {
    "espnScoreProjection": 10.082827437656086,
    "espnLowScore": 3.099,
    "espnHighScore": 17.48,
    "espnOutsideProjection": 10.40167239,
    "espnSimulationProjection": 9.583
  },
  "jonnu smith": {
    "espnScoreProjection": 8.796404661669394,
    "espnLowScore": 4.393,
    "espnHighScore": 13.195,
    "espnOutsideProjection": 8.1249254,
    "espnSimulationProjection": 7.995
  },
  "rashod bateman": {
    "espnScoreProjection": 6.4107562962362294,
    "espnLowScore": 2.114,
    "espnHighScore": 11.134,
    "espnOutsideProjection": 6.6,
    "espnSimulationProjection": 5.264
  },
  "isaiah davis": {
    "espnScoreProjection": 6.629505994273616,
    "espnLowScore": 1.922,
    "espnHighScore": 9.975,
    "espnOutsideProjection": 6.68223786,
    "espnSimulationProjection": 5.187
  },
  "justice hill": {
    "espnScoreProjection": 8.554245824505571,
    "espnLowScore": 3.432,
    "espnHighScore": 14.564,
    "espnOutsideProjection": 8,
    "espnSimulationProjection": 7.723
  },
  "noah fant": {
    "espnScoreProjection": 5.513762161258747,
    "espnLowScore": 2.148,
    "espnHighScore": 12.137,
    "espnOutsideProjection": 7.06136688,
    "espnSimulationProjection": 4.857
  },
  "luther burden": {
    "espnScoreProjection": 7.9403200905633575,
    "espnLowScore": 1.861,
    "espnHighScore": 12.867,
    "espnOutsideProjection": 4.79954484,
    "espnSimulationProjection": 7.364
  },
  "pat freiermuth": {
    "espnScoreProjection": 6.433067267363325,
    "espnLowScore": 2.13,
    "espnHighScore": 11.301,
    "espnOutsideProjection": 5.1470044,
    "espnSimulationProjection": 6.716
  },
  "isaiah bond": {
    "espnScoreProjection": 7.11046351943471,
    "espnLowScore": 1.835,
    "espnHighScore": 11.482,
    "espnOutsideProjection": 3.96916436,
    "espnSimulationProjection": 6.658
  },
  "treveyon henderson": {
    "espnScoreProjection": 8.425827597425434,
    "espnLowScore": 3.355,
    "espnHighScore": 14.384,
    "espnOutsideProjection": 8.28081275,
    "espnSimulationProjection": 7.581
  },
  "andrei iosivas": {
    "espnScoreProjection": 9.19518231964192,
    "espnLowScore": 4.273,
    "espnHighScore": 17.105,
    "espnOutsideProjection": 5.4,
    "espnSimulationProjection": 9.081
  },
  "demario douglas": {
    "espnScoreProjection": 6.8973411548268935,
    "espnLowScore": 2.722,
    "espnHighScore": 12.232,
    "espnOutsideProjection": 5.96854819,
    "espnSimulationProjection": 7.477
  },
  "chig okonkwo": {
    "espnScoreProjection": 7.2526533657517085,
    "espnLowScore": 2.704,
    "espnHighScore": 11.53,
    "espnOutsideProjection": 8.15306037,
    "espnSimulationProjection": 7.117
  },
  "allen lazard": {
    "espnScoreProjection": 10.197041449505106,
    "espnLowScore": 5.262,
    "espnHighScore": 18.256,
    "espnOutsideProjection": 6.7,
    "espnSimulationProjection": 10.455
  },
  "jahan dotson": {
    "espnScoreProjection": 10.662026238500102,
    "espnLowScore": 5.217,
    "espnHighScore": 18.81,
    "espnOutsideProjection": 7.9,
    "espnSimulationProjection": 10.723
  },
  "samaje perine": {
    "espnScoreProjection": 7.161397857209858,
    "espnLowScore": 2.581,
    "espnHighScore": 11.375,
    "espnOutsideProjection": 7.14168359,
    "espnSimulationProjection": 5.563
  },
  "tyrone tracy": {
    "espnScoreProjection": 6.233164906554228,
    "espnLowScore": 1.87,
    "espnHighScore": 9.601,
    "espnOutsideProjection": 5.27784241,
    "espnSimulationProjection": 5.008
  },
  "darnell washington": {
    "espnScoreProjection": 5.334930111677799,
    "espnLowScore": 2.014,
    "espnHighScore": 15.341,
    "espnOutsideProjection": 5.85822702,
    "espnSimulationProjection": 4.3
  },
  "kavontae turpin": {
    "espnScoreProjection": 7.567357406869331,
    "espnLowScore": 1.749,
    "espnHighScore": 12.982,
    "espnOutsideProjection": 4.95945564,
    "espnSimulationProjection": 7.366
  },
  "isaiah likely": {
    "espnScoreProjection": 3.4024913632243035,
    "espnLowScore": 1.891,
    "espnHighScore": 9.751,
    "espnOutsideProjection": 4.8,
    "espnSimulationProjection": 4.023
  },
  "david njoku": {
    "espnScoreProjection": 7.95588712317956,
    "espnLowScore": 3.72,
    "espnHighScore": 12.412,
    "espnOutsideProjection": 10.24238674,
    "espnSimulationProjection": 8.066
  },
  "kareem hunt": {
    "espnScoreProjection": 7.246566129095466,
    "espnLowScore": 2.597,
    "espnHighScore": 11.233,
    "espnOutsideProjection": 7.03129136,
    "espnSimulationProjection": 5.552
  },
  "sean tucker": {
    "espnScoreProjection": 5.7678822724572285,
    "espnLowScore": 1.826,
    "espnHighScore": 9.207,
    "espnOutsideProjection": 5.66146457,
    "espnSimulationProjection": 4.83
  },
  "deandre hopkins": {
    "espnScoreProjection": 5.115634516467068,
    "espnLowScore": 1.881,
    "espnHighScore": 11.363,
    "espnOutsideProjection": 4.7,
    "espnSimulationProjection": 4.453
  },
  "jeremy mcnichols": {
    "espnScoreProjection": 5.488934819558133,
    "espnLowScore": 2.066,
    "espnHighScore": 8.298,
    "espnOutsideProjection": 5.57546604,
    "espnSimulationProjection": 4.813
  },
  "liljordan humphrey": {
    "espnScoreProjection": 7.430253169396082,
    "espnLowScore": 3.9,
    "espnHighScore": 8.467,
    "espnOutsideProjection": 3.9,
    "espnSimulationProjection": 7.43
  },
  "emanuel wilson": {
    "espnScoreProjection": 4.859618723197748,
    "espnLowScore": 1.575,
    "espnHighScore": 7.65,
    "espnOutsideProjection": 4.62516131,
    "espnSimulationProjection": 4.253
  },
  "jaylin lane": {
    "espnScoreProjection": 3.5209208,
    "espnLowScore": -0.035,
    "espnHighScore": 7.076,
    "espnOutsideProjection": 3.5209208,
    "espnSimulationProjection": 3.521
  },
  "taysom hill": {
    "espnScoreProjection": 4.78056515,
    "espnLowScore": -1.082,
    "espnHighScore": 10.644,
    "espnOutsideProjection": 4.78056515,
    "espnSimulationProjection": 4.781
  },
  "gunnar helm": {
    "espnScoreProjection": 7.115470147324467,
    "espnLowScore": 2.797,
    "espnHighScore": 11.086,
    "espnOutsideProjection": 6.48769301,
    "espnSimulationProjection": 6.942
  },
  "brian robinson": {
    "espnScoreProjection": 4.389647870095977,
    "espnLowScore": 1.09,
    "espnHighScore": 5.595,
    "espnOutsideProjection": 3.47054433,
    "espnSimulationProjection": 3.342
  },
  "nick westbrookikhine": {
    "espnScoreProjection": 10.206556045702353,
    "espnLowScore": 5.264,
    "espnHighScore": 18.259,
    "espnOutsideProjection": 6.5143482,
    "espnSimulationProjection": 10.459
  },
  "juju smithschuster": {
    "espnScoreProjection": 4.108341594937027,
    "espnLowScore": 1.661,
    "espnHighScore": 12.647,
    "espnOutsideProjection": 3.14209111,
    "espnSimulationProjection": 3.546
  },
  "jatavion sanders": {
    "espnScoreProjection": 6.175190452996803,
    "espnLowScore": 5.139,
    "espnHighScore": 7.212,
    "espnOutsideProjection": 6.7,
    "espnSimulationProjection": 6.175
  },
  "chris moore": {
    "espnScoreProjection": 4.03943796,
    "espnLowScore": 1.795,
    "espnHighScore": 8.522,
    "espnOutsideProjection": 4.03943796,
    "espnSimulationProjection": 4.171
  },
  "jerome ford": {
    "espnScoreProjection": 5.042223936847113,
    "espnLowScore": 1.615,
    "espnHighScore": 7.796,
    "espnOutsideProjection": 4.99094277,
    "espnSimulationProjection": 4.34
  },
  "luke mccaffrey": {
    "espnScoreProjection": 2.10875152,
    "espnLowScore": 0.785,
    "espnHighScore": 7.539,
    "espnOutsideProjection": 2.10875152,
    "espnSimulationProjection": 2.511
  },
  "pat bryant": {
    "espnScoreProjection": 4.138460198171767,
    "espnLowScore": 1.662,
    "espnHighScore": 12.655,
    "espnOutsideProjection": 3.52212619,
    "espnSimulationProjection": 3.548
  },
  "mack hollins": {
    "espnScoreProjection": 8.427033041146775,
    "espnLowScore": 3.071,
    "espnHighScore": 13.594,
    "espnOutsideProjection": 4.5,
    "espnSimulationProjection": 8.333
  },
  "brandin cooks": {
    "espnScoreProjection": 3.7647940694908044,
    "espnLowScore": 1.736,
    "espnHighScore": 9.408,
    "espnOutsideProjection": 2.64252677,
    "espnSimulationProjection": 4.356
  },
  "tyquan thornton": {
    "espnScoreProjection": 2.768323014140023,
    "espnLowScore": -0.868,
    "espnHighScore": 6.404,
    "espnOutsideProjection": 1.9171929,
    "espnSimulationProjection": 2.768
  },
  "kameron johnson": {
    "espnScoreProjection": 8.612743447878255,
    "espnLowScore": 3.209,
    "espnHighScore": 13.745,
    "espnOutsideProjection": 4.47794527,
    "espnSimulationProjection": 8.477
  },
  "tommy tremble": {
    "espnScoreProjection": 3.702052152288303,
    "espnLowScore": -0.261,
    "espnHighScore": 7.665,
    "espnOutsideProjection": 3.42616089,
    "espnSimulationProjection": 3.702
  },
  "ollie gordon": {
    "espnScoreProjection": 4.862003571409934,
    "espnLowScore": 1.575,
    "espnHighScore": 7.65,
    "espnOutsideProjection": 4.56130865,
    "espnSimulationProjection": 4.253
  },
  "elijah moore": {
    "espnScoreProjection": "",
    "espnLowScore": "",
    "espnHighScore": 7.542,
    "espnOutsideProjection": "",
    "espnSimulationProjection": 2.35
  },
  "jaydon blue": {
    "espnScoreProjection": 4.077433193893986,
    "espnLowScore": 0.919,
    "espnHighScore": 5.753,
    "espnOutsideProjection": 3.26171194,
    "espnSimulationProjection": 3.336
  },
  "dawson knox": {
    "espnScoreProjection": 3.6889701397693226,
    "espnLowScore": -0.277,
    "espnHighScore": 7.655,
    "espnOutsideProjection": 3.70138818,
    "espnSimulationProjection": 3.689
  },
  "devin neal": {
    "espnScoreProjection": 4.6706541121149545,
    "espnLowScore": 1.336,
    "espnHighScore": 6.986,
    "espnOutsideProjection": 4.66355872,
    "espnSimulationProjection": 3.236
  },
  "jalen tolbert": {
    "espnScoreProjection": 4.26617645,
    "espnLowScore": 1.738,
    "espnHighScore": 9.598,
    "espnOutsideProjection": 4.26617645,
    "espnSimulationProjection": 3.87
  },
  "ty johnson": {
    "espnScoreProjection": 3.1604120925856822,
    "espnLowScore": 0.679,
    "espnHighScore": 5.642,
    "espnOutsideProjection": 2.70234248,
    "espnSimulationProjection": 3.16
  },
  "curtis samuel": {
    "espnScoreProjection": -0.004611546721057505,
    "espnLowScore": "",
    "espnHighScore": 7.547,
    "espnOutsideProjection": "",
    "espnSimulationProjection": 2.348
  },
  "demarcus robinson": {
    "espnScoreProjection": 6.921745059297123,
    "espnLowScore": 2.73,
    "espnHighScore": 12.234,
    "espnOutsideProjection": 4.4,
    "espnSimulationProjection": 7.482
  },
  "chris rodriguez": {
    "espnScoreProjection": 2.566500192136644,
    "espnLowScore": 0.181,
    "espnHighScore": 5.571,
    "espnOutsideProjection": 1.81875146,
    "espnSimulationProjection": 2.876
  },
  "austin hooper": {
    "espnScoreProjection": 2.2770656441562096,
    "espnLowScore": 1.761,
    "espnHighScore": 8.794,
    "espnOutsideProjection": 2.1,
    "espnSimulationProjection": 3.668
  },
  "noah gray": {
    "espnScoreProjection": 3.191896979327076,
    "espnLowScore": 1.836,
    "espnHighScore": 9.22,
    "espnOutsideProjection": 2.99277824,
    "espnSimulationProjection": 3.838
  },
  "jimmy horn": {
    "espnScoreProjection": 7.1782187440117795,
    "espnLowScore": 1.875,
    "espnHighScore": 11.499,
    "espnOutsideProjection": 3.89859068,
    "espnSimulationProjection": 6.687
  },
  "roman wilson": {
    "espnScoreProjection": 2.625829719911497,
    "espnLowScore": -0.836,
    "espnHighScore": 6.836,
    "espnOutsideProjection": 1.6,
    "espnSimulationProjection": 3
  },
  "dylan sampson": {
    "espnScoreProjection": 3.336265873042521,
    "espnLowScore": 0.906,
    "espnHighScore": 5.767,
    "espnOutsideProjection": 2.44862984,
    "espnSimulationProjection": 3.336
  },
  "john metchie": {
    "espnScoreProjection": 0.4,
    "espnLowScore": 0.4,
    "espnHighScore": 7.172,
    "espnOutsideProjection": 0.4,
    "espnSimulationProjection": 2.503
  }
}